pysvn/__init__.py
pysvn/client.py
pysvn/constants.py
pysvn/errors.py
pysvn/models.py
pysvn/utils.py
pysubversion-1.0.1.dist-info/LICENSE
pysubversion-1.0.1.dist-info/METADATA
pysubversion-1.0.1.dist-info/WHEEL
pysubversion-1.0.1.dist-info/top_level.txt
pysubversion-1.0.1.dist-info/RECORD
