Metadata-Version: 2.1
Name: pysubversion
Version: 1.0.1
Summary: Svn for python.
Home-page: https://github.com/ryanbender2/pysvn
Author: Ryan Bender
Author-email: ryan.bender@cfacorp.com
License: BSD License
Keywords: svn,pysvn,subversion
Platform: any
Classifier: License :: OSI Approved :: BSD License
Classifier: Programming Language :: Python :: 3
Classifier: Development Status :: 4 - Beta
Classifier: Operating System :: OS Independent
License-File: LICENSE
